{
    "LS_COLORS": {
        "branch": "master",
        "description": "A collection of LS_COLORS definitions; needs your contribution!",
        "homepage": "",
        "owner": "trapd00r",
        "repo": "LS_COLORS",
        "rev": "2957904dbd4156b7980e3450233f811073132023",
        "sha256": "1wnzaay4r6sbqnxylpc31pwsq89km8y5f9caf0fq60lfabg139g3",
        "type": "tarball",
        "url": "https://github.com/trapd00r/LS_COLORS/archive/2957904dbd4156b7980e3450233f811073132023.tar.gz",
        "url_template": "https://github.com/<owner>/<repo>/archive/<rev>.tar.gz"
    },
    "NUR": {
        "branch": "master",
        "description": "Nix User Repository: User contributed nix packages [maintainer=@Mic92]",
        "homepage": "",
        "owner": "nix-community",
        "repo": "NUR",
        "rev": "3525ed4599ba5fca65e235541d80720b6bf78a96",
        "sha256": "1p0qa9bs8k0jhkdkyvxfcpi2hz2n8d61c63ps7mavk9z3zgnx20j",
        "type": "tarball",
        "url": "https://github.com/nix-community/NUR/archive/3525ed4599ba5fca65e235541d80720b6bf78a96.tar.gz",
        "url_template": "https://github.com/<owner>/<repo>/archive/<rev>.tar.gz"
    },
    "gitignore": {
        "branch": "master",
        "description": "A collection of useful .gitignore templates",
        "homepage": "",
        "owner": "github",
        "repo": "gitignore",
        "rev": "991e760c1c6d50fdda246e0178b9c58b06770b90",
        "sha256": "14k4v4pf56m6ppfg33w44g64bajvm997x8c8n2hax3yqb3w6qqpj",
        "type": "tarball",
        "url": "https://github.com/github/gitignore/archive/991e760c1c6d50fdda246e0178b9c58b06770b90.tar.gz",
        "url_template": "https://github.com/<owner>/<repo>/archive/<rev>.tar.gz"
    },
    "home-manager": {
        "branch": "master",
        "description": "Manage a user environment using Nix",
        "homepage": "https://rycee.gitlab.io/home-manager/",
        "owner": "nix-community",
        "repo": "home-manager",
        "rev": "5f6364fc28065d6b26423512e14207ce0bffb27a",
        "sha256": "090z94rwmdxbh9vzrg30b2ndfrjcm7rg08gd1ng2kfpb81agnijc",
        "type": "tarball",
        "url": "https://github.com/nix-community/home-manager/archive/5f6364fc28065d6b26423512e14207ce0bffb27a.tar.gz",
        "url_template": "https://github.com/<owner>/<repo>/archive/<rev>.tar.gz"
    },
    "ijohanne-nur-packages": {
        "branch": "master",
        "description": "NUR packages",
        "homepage": null,
        "owner": "ijohanne",
        "repo": "nur-packages",
        "rev": "d284c0a6b2d238dc21b2f162cf2a1de9d3d25115",
        "sha256": "0gf0rh68lh0jxnsjnr86p2b92nxhnaq5dw0dbgcxgph1r6ql245p",
        "type": "tarball",
        "url": "https://github.com/ijohanne/nur-packages/archive/d284c0a6b2d238dc21b2f162cf2a1de9d3d25115.tar.gz",
        "url_template": "https://github.com/<owner>/<repo>/archive/<rev>.tar.gz"
    },
    "mozilla-overlay": {
        "branch": "master",
        "description": "Mozilla overlay",
        "homepage": null,
        "owner": "mozilla",
        "repo": "nixpkgs-mozilla",
        "rev": "4a07484cf0e49047f82d83fd119acffbad3b235f",
        "sha256": "1qg9gj6xlz2zsbdsijn5z2km29lc90qzwkcm9p1rpn4bcmkknq1r",
        "type": "tarball",
        "url": "https://github.com/mozilla/nixpkgs-mozilla/archive/4a07484cf0e49047f82d83fd119acffbad3b235f.tar.gz",
        "url_template": "https://github.com/<owner>/<repo>/archive/<rev>.tar.gz"
    },
    "niv": {
        "branch": "master",
        "description": "Easy dependency management for Nix projects",
        "homepage": "https://github.com/nmattia/niv",
        "owner": "nmattia",
        "repo": "niv",
        "rev": "e0ca65c81a2d7a4d82a189f1e23a48d59ad42070",
        "sha256": "1pq9nh1d8nn3xvbdny8fafzw87mj7gsmp6pxkdl65w2g18rmcmzx",
        "type": "tarball",
        "url": "https://github.com/nmattia/niv/archive/e0ca65c81a2d7a4d82a189f1e23a48d59ad42070.tar.gz",
        "url_template": "https://github.com/<owner>/<repo>/archive/<rev>.tar.gz"
    },
    "nix-gitignore": {
        "branch": "master",
        "description": "Nix function for filtering local git sources",
        "homepage": "",
        "owner": "hercules-ci",
        "repo": "gitignore",
        "rev": "211907489e9f198594c0eb0ca9256a1949c9d412",
        "sha256": "06j7wpvj54khw0z10fjyi31kpafkr6hi1k0di13k1xp8kywvfyx8",
        "type": "tarball",
        "url": "https://github.com/hercules-ci/gitignore/archive/211907489e9f198594c0eb0ca9256a1949c9d412.tar.gz",
        "url_template": "https://github.com/<owner>/<repo>/archive/<rev>.tar.gz"
    },
    "nixpkgs": {
        "branch": "nixos-unstable-small",
        "description": "Nix Packages collection",
        "homepage": null,
        "owner": "NixOS",
        "repo": "nixpkgs",
        "rev": "d0044b0e7d531a7a28d4552582b98e8b3953c6cb",
        "sha256": "01vg18lj4hv2q5vw5in5vv65m88xyikw53614rgrjnga6jbypnb6",
        "type": "tarball",
        "url": "https://github.com/NixOS/nixpkgs/archive/d0044b0e7d531a7a28d4552582b98e8b3953c6cb.tar.gz",
        "url_template": "https://github.com/<owner>/<repo>/archive/<rev>.tar.gz"
    },
    "pre-commit-hooks-nix": {
        "branch": "master",
        "description": "Seamless integration of https://pre-commit.com git hooks with Nix.",
        "homepage": "",
        "owner": "cachix",
        "repo": "pre-commit-hooks.nix",
        "rev": "397f0713d007250a2c7a745e555fa16c5dc8cadb",
        "sha256": "0hjbq4pf8a2qdndx0xdb3yjhx9l3l5grk4mlk78vw4zm32fgyrq2",
        "type": "tarball",
        "url": "https://github.com/cachix/pre-commit-hooks.nix/archive/397f0713d007250a2c7a745e555fa16c5dc8cadb.tar.gz",
        "url_template": "https://github.com/<owner>/<repo>/archive/<rev>.tar.gz"
    },
    "ranger_devicons": {
        "branch": "main",
        "description": "Ranger plugin that adds file glyphs / icon support to Ranger",
        "homepage": "",
        "owner": "alexanderjeurissen",
        "repo": "ranger_devicons",
        "rev": "e02b6a3203411b76616a0e4328245bf8b47c5dcc",
        "sha256": "19b06p3icpb214kpbf7irlyy813ax12i2jhibhxd2nflz9n66pg9",
        "type": "tarball",
        "url": "https://github.com/alexanderjeurissen/ranger_devicons/archive/e02b6a3203411b76616a0e4328245bf8b47c5dcc.tar.gz",
        "url_template": "https://github.com/<owner>/<repo>/archive/<rev>.tar.gz"
    }
}
